{
  "lastExecuted": "2022-01-22T19:56:48.564Z",
  "checked": {
    "siddharth2798": {
      "owner": "siddharth2798",
      "notFound": true,
      "lastExecuted": "2022-01-22T19:54:14.966Z"
    },
    "danaoshiro": {
      "owner": "danaoshiro",
      "notFound": true,
      "lastExecuted": "2022-01-22T19:54:14.966Z"
    },
    "chodges7": {
      "owner": "chodges7",
      "notFound": false,
      "lastExecuted": "2022-01-22T19:54:14.966Z"
    },
    "sobingt": {
      "owner": "sobingt",
      "notFound": false,
      "lastExecuted": "2022-01-22T19:54:14.966Z"
    },
    "prophen": {
      "owner": "prophen",
      "notFound": false,
      "lastExecuted": "2022-01-22T19:54:14.966Z"
    },
    "djdefi": {
      "owner": "djdefi",
      "notFound": false,
      "lastExecuted": "2022-01-22T19:54:14.966Z"
    },
    "msradam": {
      "owner": "msradam",
      "notFound": false,
      "lastExecuted": "2022-01-22T19:54:14.966Z"
    },
    "vincentmuriuki": {
      "owner": "vincentmuriuki",
      "notFound": true,
      "lastExecuted": "2022-01-22T19:56:48.564Z"
    },
    "AlexVCS": {
      "owner": "AlexVCS",
      "notFound": true,
      "lastExecuted": "2022-01-22T19:56:48.564Z"
    },
    "LevinGar": {
      "owner": "LevinGar",
      "notFound": true,
      "lastExecuted": "2022-01-22T19:56:48.564Z"
    },
    "talktalkmake": {
      "owner": "talktalkmake",
      "notFound": true,
      "lastExecuted": "2022-01-22T19:56:48.564Z"
    },
    "HaigNalbandian": {
      "owner": "HaigNalbandian",
      "notFound": true,
      "lastExecuted": "2022-01-22T19:56:48.564Z"
    },
    "seth808rose": {
      "owner": "seth808rose",
      "notFound": true,
      "lastExecuted": "2022-01-22T19:56:48.564Z"
    },
    "manisuec": {
      "owner": "manisuec",
      "notFound": true,
      "lastExecuted": "2022-01-22T19:56:48.564Z"
    },
    "anis00723": {
      "owner": "anis00723",
      "notFound": false,
      "lastExecuted": "2022-01-22T19:56:48.564Z"
    },
    "udhaykumarbala": {
      "owner": "udhaykumarbala",
      "notFound": false,
      "lastExecuted": "2022-01-22T19:56:48.564Z"
    },
    "ramonh": {
      "owner": "ramonh",
      "notFound": false,
      "lastExecuted": "2022-01-22T19:56:48.564Z"
    },
    "Wisheechia": {
      "owner": "Wisheechia",
      "notFound": false,
      "lastExecuted": "2022-01-22T19:56:48.564Z"
    },
    "thebiblelover7": {
      "owner": "thebiblelover7",
      "notFound": false,
      "lastExecuted": "2022-01-22T19:56:48.564Z"
    }
  }
}